Workbook
Name Aporte: Planilha2!$C$16
Name Dividendos_mensais: Planilha2!$B$20
Name Patrimonio: Planilha2!$C$19
Name Qtd_anos: Planilha2!$C$17
Name Rendimento_carteira: Planilha2!$C$12
Name Salario: Planilha2!$C$11
Name Taxa_mensal: Planilha2!$C$18

Sheet Planilha2
B10: Configuraçãoes
B11: Salário | C11: 2000
B12: Rendimentos Carteira | C12: 0.006
B13: Sugestão investimento | C13: =C11*30% -> 600
B15: INVESTIMENTO MENSAL
B16: Quanto investir por mês? | C16: 200
B17: Por quantos anos investir? | C17: 5
B18: Taxa de rendimentos mensal? | C18: 0.01079
B19: Patrimônio acumulado? | C19: =FV(Taxa_mensal,Qtd_anos*12,-Aporte) -> 16755.383
B20: Dividendos mensais? | C20: =Patrimonio*Rendimento_carteira -> 100.5323
B22: Cenários | D22: Dividendo
A23: 2 | B23: Quanto em 2 anos? | C23: =FV(Taxa_mensal,A23*12,-Aporte) -> 5445.5255 | D23: =C23*Rendimento_carteira -> 32.673153
A24: 5 | B24: Quanto em 5 anos? | C24: =FV(Taxa_mensal,A24*12,-Aporte) -> 16755.383 | D24: =C24*Rendimento_carteira -> 100.5323
A25: 10 | B25: Quanto em 10 anos? | C25: =FV(Taxa_mensal,A25*12,-Aporte) -> 48656.843 | D25: =C25*Rendimento_carteira -> 291.94106
A26: 20 | B26: Quanto em 20 anos? | C26: =FV(Taxa_mensal,A26*12,-Aporte) -> 225039.68 | D26: =C26*Rendimento_carteira -> 1350.2381
A27: 30 | B27: Quanto em 30 anos? | C27: =FV(Taxa_mensal,A27*12,-Aporte) -> 864433.93 | D27: =C27*Rendimento_carteira -> 5186.6036
B32: Perfil | C32: Moderado
B33: Valor a ser investido por mês | C33: =Aporte -> 200
B35: Tipo de FII | C35: Percential Sugerido | D35: Valores
B36: PAPEL | C36: =VLOOKUP($C$32&"-"&B36,Planilha1!$A:$D,4,FALSE) -> 0.32 | D36: =$C$33*C36 -> 64
B37: TIJOLO | C37: =VLOOKUP($C$32&"-"&B37,Planilha1!$A:$D,4,FALSE) -> 0.4 | D37: =$C$33*C37 -> 80
B38: HÍBRIDOS | C38: =VLOOKUP($C$32&"-"&B38,Planilha1!$A:$D,4,FALSE) -> 0.08 | D38: =$C$33*C38 -> 16
B39: FOFs | C39: =VLOOKUP($C$32&"-"&B39,Planilha1!$A:$D,4,FALSE) -> 0.1 | D39: =$C$33*C39 -> 20
B40: DESENVOLVIMENTO | C40: =VLOOKUP($C$32&"-"&B40,Planilha1!$A:$D,4,FALSE) -> 0.05 | D40: =$C$33*C40 -> 10
B41: HOTELARIAS | C41: =VLOOKUP($C$32&"-"&B41,Planilha1!$A:$D,4,FALSE) -> 0.05 | D41: =$C$33*C41 -> 10
D42: =SUM(D36:D41) -> 200

Sheet Planilha1
A1: Chave | B1: Perfil | C1: Tipos de FII | D1: %
A2: =B2&"-"&C2 -> Conservador-PAPEL | B2: Conservador | C2: PAPEL | D2: 0.3
A3: =B3&"-"&C3 -> Conservador-TIJOLO | B3: Conservador | C3: TIJOLO | D3: 0.5 | H3: %
A4: =B4&"-"&C4 -> Conservador-HÍBRIDOS | B4: Conservador | C4: HÍBRIDOS | D4: 0.1 | G4: Moderado-TIJOLO | H4: =VLOOKUP(G4,$A:$D,4,FALSE) -> 0.4
A5: =B5&"-"&C5 -> Conservador-FOFs | B5: Conservador | C5: FOFs | D5: 0.1
A6: =B6&"-"&C6 -> Conservador-DESENVOLVIMENTO | B6: Conservador | C6: DESENVOLVIMENTO | D6: 0
A7: =B7&"-"&C7 -> Conservador-HOTELARIAS | B7: Conservador | C7: HOTELARIAS | D7: 0
A8: =B8&"-"&C8 -> Moderado-PAPEL | B8: Moderado | C8: PAPEL | D8: 0.32
A9: =B9&"-"&C9 -> Moderado-TIJOLO | B9: Moderado | C9: TIJOLO | D9: 0.4
A10: =B10&"-"&C10 -> Moderado-HÍBRIDOS | B10: Moderado | C10: HÍBRIDOS | D10: 0.08
A11: =B11&"-"&C11 -> Moderado-FOFs | B11: Moderado | C11: FOFs | D11: 0.1
A12: =B12&"-"&C12 -> Moderado-DESENVOLVIMENTO | B12: Moderado | C12: DESENVOLVIMENTO | D12: 0.05
A13: =B13&"-"&C13 -> Moderado-HOTELARIAS | B13: Moderado | C13: HOTELARIAS | D13: 0.05
A14: =B14&"-"&C14 -> Agressivo-PAPEL | B14: Agressivo | C14: PAPEL | D14: 0.5
A15: =B15&"-"&C15 -> Agressivo-TIJOLO | B15: Agressivo | C15: TIJOLO | D15: 0.1
A16: =B16&"-"&C16 -> Agressivo-HÍBRIDOS | B16: Agressivo | C16: HÍBRIDOS | D16: 0.05
... A19: =B19&"-"&C19 -> Agressivo-HOTELARIAS | B19: Agressivo | C19: HOTELARIAS | D19: 0.1
